tootapari/__init__.py
tootapari/napari.yaml
tootapari/widget.py
tootapari/_tests/__init__.py
tootapari-0.0.1.dist-info/LICENSE
tootapari-0.0.1.dist-info/METADATA
tootapari-0.0.1.dist-info/WHEEL
tootapari-0.0.1.dist-info/entry_points.txt
tootapari-0.0.1.dist-info/top_level.txt
tootapari-0.0.1.dist-info/RECORD
