Metadata-Version: 2.1
Name: tootapari
Version: 0.0.1
Summary: A plugin to send Mastodon toots from napari
Home-page: https://github.com/kephale/tootapari
Author: Kyle Harrington
Author-email: czi@kyleharrington.com
License: BSD-3-Clause
Project-URL: Bug Tracker, https://github.com/kephale/tootapari/issues
Project-URL: Documentation, https://github.com/kephale/tootapari#README.md
Project-URL: Source Code, https://github.com/kephale/tootapari
Project-URL: User Support, https://github.com/kephale/tootapari/issues
Classifier: Development Status :: 2 - Pre-Alpha
Classifier: Framework :: napari
Classifier: Intended Audience :: Developers
Classifier: License :: OSI Approved :: BSD License
Classifier: Operating System :: OS Independent
Classifier: Programming Language :: Python
Classifier: Programming Language :: Python :: 3
Classifier: Programming Language :: Python :: 3 :: Only
Classifier: Programming Language :: Python :: 3.8
Classifier: Programming Language :: Python :: 3.9
Classifier: Programming Language :: Python :: 3.10
Classifier: Topic :: Scientific/Engineering :: Image Processing
Requires-Python: >=3.8
License-File: LICENSE
Requires-Dist: numpy
Requires-Dist: python-dotenv
Requires-Dist: Mastodon.py
Provides-Extra: testing
Requires-Dist: tox ; extra == 'testing'
Requires-Dist: pytest ; extra == 'testing'
Requires-Dist: pytest-cov ; extra == 'testing'
